mbd_pay/__init__.py
mbd_pay/client.py
mbd_pay/sign.py
mbd_pay/types.py
mbd_pay-0.1.4.dist-info/LICENSE
mbd_pay-0.1.4.dist-info/WHEEL
mbd_pay-0.1.4.dist-info/METADATA
mbd_pay-0.1.4.dist-info/RECORD
