Metadata-Version: 2.1
Name: mbd-pay
Version: 0.1.4
Summary: 面包多支付SDK - https://mbd.pub/
Home-page: https://github.com/shaoxyz/mbd_pay
License: MIT
Author: shaoxyz
Author-email: shwb95@163.com
Requires-Python: >=3.7,<4.0
Classifier: License :: OSI Approved :: MIT License
Classifier: Operating System :: OS Independent
Classifier: Programming Language :: Python :: 3
Classifier: Programming Language :: Python :: 3.7
Classifier: Programming Language :: Python :: 3.8
Classifier: Programming Language :: Python :: 3.9
Requires-Dist: pydantic (>=1.8.1,<2.0.0)
Requires-Dist: requests (>=2.25.1,<3.0.0)
Project-URL: Repository, https://github.com/shaoxyz/mbd_pay
